pkglink/__init__.py
pkglink/argparse.py
pkglink/config.py
pkglink/execution_plan.py
pkglink/installation.py
pkglink/models.py
pkglink/package_discovery.py
pkglink/parsing.py
pkglink/project_structure.py
pkglink/py.typed
pkglink/setup.py
pkglink/symlinks.py
pkglink/uvx.py
pkglink/version.py
pkglink/cli/__init__.py
pkglink/cli/common.py
pkglink/cli/pkglink.py
pkglink/cli/subparsers/__init__.py
pkglink/cli/subparsers/_shared.py
pkglink/cli/subparsers/link.py
pkglink/cli/subparsers/sync.py
pkglink/cli/subparsers/tool.py
pkglink-1.1.0.dist-info/METADATA
pkglink-1.1.0.dist-info/WHEEL
pkglink-1.1.0.dist-info/entry_points.txt
pkglink-1.1.0.dist-info/licenses/LICENSE
pkglink-1.1.0.dist-info/RECORD
