Metadata-Version: 2.4
Name: pkglink
Version: 1.1.0
Summary: Create symlinks to python package directories
Author: hotdog-werx
License-Expression: MIT
License-File: LICENSE
Requires-Python: >=3.11
Requires-Dist: argcomplete<4,>=3.6.2
Requires-Dist: hotlog>=0.1.1
Requires-Dist: pathspec<1,>=0.12.0
Requires-Dist: pydantic>=2.0.0
Requires-Dist: pyyaml<7,>=6.0
Requires-Dist: rich<15,>=14.0.0
Requires-Dist: structlog<26,>=25.4.0
Requires-Dist: tomli-w>=1.2.0
